df_processors/__init__.py
df_processors/_utils.py
df_processors/create.py
df_processors/impute.py
df_processors/normalize.py
df_processors-0.1.3.dist-info/METADATA
df_processors-0.1.3.dist-info/WHEEL
df_processors-0.1.3.dist-info/RECORD
